{
  "miniprogramRoot": "dist/",
  "projectname": "safety-scout-miniprogram",
  "description": "Safety Scout 工地安全隐患识别小程序",
  "appid": "touristappid",
  "setting": {
    "urlCheck": false,
    "es6": true,
    "enhance": true,
    "postcss": true,
    "preloadBackgroundData": false,
    "minified": false,
    "newFeature": false,
    "autoAudits": false,
    "uglifyFileName": false,
    "uploadWithSourceMap": true,
    "useIsolateContext": true,
    "nodeModules": false,
    "enableEngineNative": false,
    "useMultiFrameRuntime": true,
    "useApiHook": true,
    "useApiHostProcess": true
  },
  "compileType": "miniprogram",
  "libVersion": "2.27.0",
  "condition": {}
}
